soxs/__init__.py
soxs/constants.py
soxs/cosmology.py
soxs/data.py
soxs/file_hash_registry.json
soxs/instrument.py
soxs/instrument_registry.py
soxs/mosaic.py
soxs/psf.py
soxs/response.py
soxs/simput.py
soxs/spatial.py
soxs/thermal_spectra.py
soxs/utils.py
soxs/background/__init__.py
soxs/background/diffuse.py
soxs/background/events.py
soxs/background/point_sources.py
soxs/background/spectra.py
soxs/events/__init__.py
soxs/events/images.py
soxs/events/spectra.py
soxs/events/tools.py
soxs/events/utils.py
soxs/files/acisi_particle_bkgnd.h5
soxs/files/aciss_particle_bkgnd.h5
soxs/files/halo_catalog.h5
soxs/files/hm_cxb_bkgnd.h5
soxs/files/lum_table.h5
soxs/lib/__init__.py
soxs/lib/broaden_lines.cpython-314-x86_64-linux-musl.so
soxs/lib/broaden_lines.pyx
soxs/lib/psf_cdf.cpython-314-x86_64-linux-musl.so
soxs/lib/psf_cdf.pyx
soxs/spectra/__init__.py
soxs/spectra/base.py
soxs/spectra/charge_exchange.py
soxs/spectra/foreground_absorption.py
soxs/spectra/thermal_spectra.py
soxs/tests/__init__.py
soxs/tests/conftest.py
soxs/tests/coveragerc
soxs/tests/test_bkgnd.py
soxs/tests/test_cx.py
soxs/tests/test_filter.py
soxs/tests/test_lines.py
soxs/tests/test_power_law.py
soxs/tests/test_pyspex.py
soxs/tests/test_registry.py
soxs/tests/test_simput.py
soxs/tests/test_simulate_spectrum.py
soxs/tests/test_spatial.py
soxs/tests/test_spectra.py
soxs/tests/test_thermal.py
soxs/tests/test_xstar.py
soxs/tests/utils.py
soxs-5.2.0.data/scripts/get_instrument_data
soxs-5.2.0.data/scripts/instrument_simulator
soxs-5.2.0.data/scripts/make_annulus_source
soxs-5.2.0.data/scripts/make_background_file
soxs-5.2.0.data/scripts/make_beta_model_source
soxs-5.2.0.data/scripts/make_cie_spectrum
soxs-5.2.0.data/scripts/make_cosmological_sources
soxs-5.2.0.data/scripts/make_double_beta_model_source
soxs-5.2.0.data/scripts/make_exposure_map
soxs-5.2.0.data/scripts/make_fov_source
soxs-5.2.0.data/scripts/make_image
soxs-5.2.0.dist-info/METADATA
soxs-5.2.0.dist-info/WHEEL
soxs-5.2.0.dist-info/top_level.txt
soxs-5.2.0.dist-info/RECORD
soxs-5.2.0.dist-info/licenses/COPYING.txt
