Metadata-Version: 2.4
Name: soxs
Version: 5.2.0
Summary: Simulated Observations of X-ray Sources
Home-page: https://github.com/lynx-x-ray-observatory/soxs/
Author-email: John ZuHone <jzuhone@gmail.com>
Classifier: Intended Audience :: Science/Research
Classifier: Operating System :: OS Independent
Classifier: Programming Language :: Python :: 3
Classifier: Topic :: Scientific/Engineering :: Visualization
Requires-Python: >=3.11
License-File: COPYING.txt
Requires-Dist: numpy
Requires-Dist: astropy>=4.0
Requires-Dist: tqdm
Requires-Dist: pooch
Requires-Dist: h5py>=3.0
Requires-Dist: scipy
Requires-Dist: pyyaml
Requires-Dist: regions
Requires-Dist: appdirs
Dynamic: home-page
Dynamic: license-file
